ink8/__init__.py
ink8/cli.py
ink8/kubernetes/basic-svc.yml.j2
ink8/kubernetes/kong.yml.j2
ink8/kubernetes/namespace.yml.j2
ink8/kubernetes/postgres.yml.j2
ink8/kubernetes/prometheus.yml
ink8/kubernetes/redis.yml.j2
ink8/kubernetes/routes.yml.j2
ink8/kubernetes/scylla-operator.yml
ink8/kubernetes/scylla.yml
ink8/kubernetes/vault.yml.j2
ink8-1.15.dist-info/METADATA
ink8-1.15.dist-info/WHEEL
ink8-1.15.dist-info/entry_points.txt
ink8-1.15.dist-info/top_level.txt
ink8-1.15.dist-info/zip-safe
ink8-1.15.dist-info/RECORD
